modelsearch/__init__.py
modelsearch/abstract_models.py
modelsearch/apps.py
modelsearch/conf.py
modelsearch/index.py
modelsearch/models.py
modelsearch/query.py
modelsearch/queryset.py
modelsearch/signal_handlers.py
modelsearch/tasks.py
modelsearch/utils.py
modelsearch/backends/__init__.py
modelsearch/backends/base.py
modelsearch/backends/elasticsearch7.py
modelsearch/backends/elasticsearch8.py
modelsearch/backends/elasticsearch9.py
modelsearch/backends/elasticsearchbase.py
modelsearch/backends/opensearch2.py
modelsearch/backends/opensearch3.py
modelsearch/backends/database/__init__.py
modelsearch/backends/database/fallback.py
modelsearch/backends/database/mysql/__init__.py
modelsearch/backends/database/mysql/mysql.py
modelsearch/backends/database/mysql/query.py
modelsearch/backends/database/postgres/__init__.py
modelsearch/backends/database/postgres/postgres.py
modelsearch/backends/database/postgres/query.py
modelsearch/backends/database/postgres/weights.py
modelsearch/backends/database/sqlite/__init__.py
modelsearch/backends/database/sqlite/query.py
modelsearch/backends/database/sqlite/sqlite.py
modelsearch/backends/database/sqlite/utils.py
modelsearch/management/__init__.py
modelsearch/management/commands/__init__.py
modelsearch/management/commands/rebuild_modelsearch_index.py
modelsearch/migrations/0001_initial.py
modelsearch/migrations/0002_customise_indexentry.py
modelsearch/migrations/__init__.py
modelsearch/test/settings.py
modelsearch/test/urls.py
modelsearch/test/testapp/__init__.py
modelsearch/test/testapp/apps.py
modelsearch/test/testapp/models.py
modelsearch/test/testapp/migrations/0001_initial.py
modelsearch/test/testapp/migrations/0002_advertwithcustomuuidprimarykey.py
modelsearch/test/testapp/migrations/0003_m2m_test_models.py
modelsearch/test/testapp/migrations/__init__.py
modelsearch/tests/__init__.py
modelsearch/tests/elasticsearch_common_tests.py
modelsearch/tests/test_backends.py
modelsearch/tests/test_db_backend.py
modelsearch-1.1.dist-info/licenses/LICENSE
modelsearch-1.1.dist-info/METADATA
modelsearch-1.1.dist-info/WHEEL
modelsearch-1.1.dist-info/top_level.txt
modelsearch-1.1.dist-info/RECORD
